how_is_my_bmi/__init__.py
how_is_my_bmi/bmi.py
how_is_my_bmi-0.1.1.dist-info/METADATA
how_is_my_bmi-0.1.1.dist-info/WHEEL
how_is_my_bmi-0.1.1.dist-info/top_level.txt
how_is_my_bmi-0.1.1.dist-info/RECORD
