Metadata-Version: 2.1
Name: how-is-my-bmi
Version: 0.1.1
Summary: a python library to calculate one's body mass index
Home-page: https://how_is_my_bmi.readthedocs.io/
Author: Lare Samuel Adeola
Author-email: laresamdeola@gmail.com
License: MIT
Platform: UNKNOWN
Classifier: Intended Audience :: Developers
Classifier: License :: OSI Approved :: MIT License
Classifier: Programming Language :: Python
Classifier: Programming Language :: Python :: 3
Classifier: Programming Language :: Python :: 3.6
Classifier: Programming Language :: Python :: 3.7
Classifier: Programming Language :: Python :: 3.8
Classifier: Programming Language :: Python :: 3.9
Classifier: Operating System :: OS Independent
Requires-Dist: numpy
